nidec-inventory/__init__.py
nidec-inventory/cli_parameters.py
nidec-inventory/nidec-inventory.py
nidec-inventory/helpers/__init__.py
nidec-inventory/helpers/file_helpers.py
nidec-inventory/nidec/__init__.py
nidec-inventory/nidec/drive_inventory.py
nidec-inventory/nidec/nidec_drive.py
nidec-inventory/nidec/nidec_param_file_engine.py
nidec-inventory/resources/__init__.py
nidec-inventory/resources/config.yaml
nidec-inventory/resources/es.yaml
tests/__init__.py
nidec_inventory-0.0a14.dist-info/LICENSE
nidec_inventory-0.0a14.dist-info/METADATA
nidec_inventory-0.0a14.dist-info/WHEEL
nidec_inventory-0.0a14.dist-info/top_level.txt
nidec_inventory-0.0a14.dist-info/RECORD
