Metadata-Version: 2.2
Name: nidec-inventory
Version: 0.0a14
Summary: Nidec Unidrive M motor control drives inventory generator.
Home-page: https://github.com/carlosalma/nidec-inventory
Author: Carlos Alonso Martín
Author-email: Carlos Alonso Martín <cam.codeweaver@gmail.com>
Maintainer-email: Carlos Alonso Martín <cam.codeweaver@gmail.com>
License: MIT License
Keywords: nidec,variador,accionamiento,ac drives,servo drives,high performance ac drives,m700,m300,m200
Classifier: License :: OSI Approved :: MIT License
Classifier: Development Status :: 2 - Pre-Alpha
Classifier: Environment :: Console
Classifier: Programming Language :: Python
Classifier: Topic :: Documentation
Classifier: Topic :: Office/Business
Classifier: Topic :: Utilities
License-File: LICENSE
Requires-Dist: pandas~=2.2.3
Requires-Dist: PyYAML~=6.0.2
Requires-Dist: setuptools~=75.8.2
Requires-Dist: openpyxl~=3.1.5
Dynamic: author
Dynamic: home-page
